vnstock/__init__.py
vnstock/base.py
vnstock/config.py
vnstock/api/__init__.py
vnstock/api/company.py
vnstock/api/financial.py
vnstock/api/listing.py
vnstock/api/quote.py
vnstock/api/screener.py
vnstock/api/trading.py
vnstock/botbuilder/__init__.py
vnstock/botbuilder/noti.py
vnstock/common/__init__.py
vnstock/common/cli.py
vnstock/common/vnstock.py
vnstock/common/data/__init__.py
vnstock/common/data/data_explorer.py
vnstock/common/plot/__init__.py
vnstock/common/plot/chart_wrapper.py
vnstock/core/__init__.py
vnstock/core/config/__init__.py
vnstock/core/config/const.py
vnstock/core/converter/__init__.py
vnstock/core/converter/export.py
vnstock/core/utils/__init__.py
vnstock/core/utils/browser_profiles.py
vnstock/core/utils/client.py
vnstock/core/utils/env.py
vnstock/core/utils/ext.py
vnstock/core/utils/help.py
vnstock/core/utils/launcher.py
vnstock/core/utils/logger.py
vnstock/core/utils/market.py
vnstock/core/utils/parser.py
vnstock/core/utils/transform.py
vnstock/core/utils/upgrade.py
vnstock/core/utils/user_agent.py
vnstock/core/utils/validation.py
vnstock/explorer/__init__.py
vnstock/explorer/fmarket/__init__.py
vnstock/explorer/fmarket/const.py
vnstock/explorer/fmarket/fund.py
vnstock/explorer/misc/__init__.py
vnstock/explorer/misc/exchange_rate.py
vnstock/explorer/misc/gold_price.py
vnstock/explorer/msn/__init__.py
vnstock/explorer/msn/const.py
vnstock/explorer/msn/helper.py
vnstock/explorer/msn/listing.py
vnstock/explorer/msn/models.py
vnstock/explorer/msn/quote.py
vnstock/explorer/tcbs/__init__.py
vnstock/explorer/tcbs/analysis.py
vnstock/explorer/tcbs/company.py
vnstock/explorer/tcbs/const.py
vnstock/explorer/tcbs/financial.py
vnstock/explorer/tcbs/listing.py
vnstock/explorer/tcbs/models.py
vnstock/explorer/tcbs/quote.py
vnstock/explorer/tcbs/screener.py
vnstock/explorer/tcbs/trading.py
vnstock/explorer/vci/__init__.py
vnstock/explorer/vci/analysis.py
vnstock/explorer/vci/company.py
vnstock/explorer/vci/const.py
vnstock/explorer/vci/financial.py
vnstock-3.2.5.dist-info/licenses/LICENSE.md
vnstock-3.2.5.dist-info/METADATA
vnstock-3.2.5.dist-info/WHEEL
vnstock-3.2.5.dist-info/entry_points.txt
vnstock-3.2.5.dist-info/top_level.txt
vnstock-3.2.5.dist-info/RECORD
