Metadata-Version: 2.4
Name: vnstock
Version: 3.2.5
Summary: A beginner-friendly yet powerful Python toolkit for financial analysis and automation — built to make modern investing accessible to everyone
Home-page: https://github.com/thinh-vu/vnstock
Author: Thinh Vu
Author-email: support@vnstocks.com
License: Custom: Personal, research, non-commercial; contact support@vnstocks.com for other use
Project-URL: Documentation, https://github.com/thinh-vu/vnstock
Project-URL: Source, https://github.com/thinh-vu/vnstock
Project-URL: Issue Tracker, https://github.com/thinh-vu/vnstock/issues
Keywords: vnstock,finance,vietnam,stock market,analysis,API
Classifier: Development Status :: 5 - Production/Stable
Classifier: Intended Audience :: Developers
Classifier: Intended Audience :: Education
Classifier: Intended Audience :: Financial and Insurance Industry
Classifier: Topic :: Software Development :: Libraries
Classifier: Topic :: Office/Business :: Financial :: Investment
Classifier: Programming Language :: Python :: 3
Classifier: Programming Language :: Python :: 3.10
Classifier: Programming Language :: Python :: 3.11
Classifier: Programming Language :: Python :: 3.12
Classifier: Operating System :: OS Independent
Classifier: License :: Other/Proprietary License
Classifier: Natural Language :: English
Classifier: Natural Language :: Vietnamese
Requires-Python: >=3.10
License-File: LICENSE.md
Requires-Dist: requests
Requires-Dist: beautifulsoup4
Requires-Dist: pandas
Requires-Dist: seaborn
Requires-Dist: openpyxl
Requires-Dist: pydantic
Requires-Dist: psutil
Requires-Dist: fake_useragent
Requires-Dist: vnstock_ezchart
Requires-Dist: click
Requires-Dist: packaging>=20.0
Requires-Dist: importlib-metadata>=1.0
Requires-Dist: tenacity
Requires-Dist: vnai>=2.0.3
Provides-Extra: dev
Requires-Dist: flake8; extra == "dev"
Provides-Extra: docs
Requires-Dist: sphinx; extra == "docs"
Requires-Dist: sphinx_rtd_theme; extra == "docs"
Provides-Extra: test
Requires-Dist: unittest; extra == "test"
Dynamic: author
Dynamic: author-email
Dynamic: classifier
Dynamic: description
Dynamic: description-content-type
Dynamic: home-page
Dynamic: keywords
Dynamic: license
Dynamic: license-file
Dynamic: project-url
Dynamic: provides-extra
Dynamic: requires-dist
Dynamic: requires-python
Dynamic: summary
